odoo/addons/purchase_order_supplierinfo_update/README.rst
odoo/addons/purchase_order_supplierinfo_update/__init__.py
odoo/addons/purchase_order_supplierinfo_update/__manifest__.py
odoo/addons/purchase_order_supplierinfo_update/i18n/purchase_order_supplierinfo_update.pot
odoo/addons/purchase_order_supplierinfo_update/models/__init__.py
odoo/addons/purchase_order_supplierinfo_update/models/purchase_order.py
odoo/addons/purchase_order_supplierinfo_update/readme/CONTRIBUTORS.rst
odoo/addons/purchase_order_supplierinfo_update/readme/DESCRIPTION.rst
odoo/addons/purchase_order_supplierinfo_update/readme/ROADMAP.rst
odoo/addons/purchase_order_supplierinfo_update/readme/USAGE.rst
odoo/addons/purchase_order_supplierinfo_update/static/description/icon.png
odoo/addons/purchase_order_supplierinfo_update/static/description/index.html
odoo/addons/purchase_order_supplierinfo_update/tests/__init__.py
odoo/addons/purchase_order_supplierinfo_update/tests/test_purchase_order_supplierinfo_update.py
odoo13_addon_purchase_order_supplierinfo_update-13.0.1.0.2.dist-info/METADATA
odoo13_addon_purchase_order_supplierinfo_update-13.0.1.0.2.dist-info/WHEEL
odoo13_addon_purchase_order_supplierinfo_update-13.0.1.0.2.dist-info/top_level.txt
odoo13_addon_purchase_order_supplierinfo_update-13.0.1.0.2.dist-info/RECORD
